pyw90/__init__.py
pyw90/auto_w90_fit.py
pyw90/auto_w90_input.yaml
pyw90/lib/__init__.py
pyw90/lib/config.py
pyw90/lib/dos.py
pyw90/lib/job.py
pyw90/lib/w90.py
pyw90/pre_w90_tool.py
pyw90/pyw90_cli.py
pyw90/utility/__init__.py
pyw90/utility/utility.py
pyw90-1.0.7.dist-info/entry_points.txt
pyw90-1.0.7.dist-info/LICENSE
pyw90-1.0.7.dist-info/WHEEL
pyw90-1.0.7.dist-info/METADATA
pyw90-1.0.7.dist-info/RECORD
